multilevel_py/__init__.py
multilevel_py/clabject_prop.py
multilevel_py/constraints.py
multilevel_py/core.py
multilevel_py/exceptions.py
multilevel_py/viz.py
multilevel_py/viz_templates/clabject.jinja2.html
tests/unit/__init__.py
tests/unit/conftest.py
tests/unit/test_clabject_prop_dict.py
tests/unit/test_constraint.py
tests/unit/test_instantiation_mechanism.py
tests/unit/test_re_init_mechanism.py
multilevel_py-0.3.0.dist-info/LICENSE
multilevel_py-0.3.0.dist-info/METADATA
multilevel_py-0.3.0.dist-info/WHEEL
multilevel_py-0.3.0.dist-info/top_level.txt
multilevel_py-0.3.0.dist-info/RECORD
