Metadata-Version: 2.1
Name: multilevel-py
Version: 0.3.0
Summary: A python framework simplifying the representation of deep domain classification hierarchies
Home-page: https://github.com/dataPuzzler/multilevel_py
Author: Lukas Seppelfricke
Author-email: data.puzzler@gmail.com
License: UNKNOWN
Keywords: multilevel,deep instantiation
Platform: UNKNOWN
Classifier: Development Status :: 3 - Alpha
Classifier: Intended Audience :: Developers
Classifier: Topic :: Software Development :: Libraries
Classifier: Topic :: Education
Classifier: License :: OSI Approved :: BSD License
Classifier: Programming Language :: Python :: 3.8
Requires-Python: >=3.5, <4
Provides-Extra: dev
Provides-Extra: test
Requires-Dist: pytest ; extra == 'test'
Requires-Dist: pytest-depends ; extra == 'test'
Provides-Extra: viz
Requires-Dist: graphviz ; extra == 'viz'
Requires-Dist: jinja2 ; extra == 'viz'
